main_cli.py
minimal_cli-0.0.1.dist-info/METADATA
minimal_cli-0.0.1.dist-info/WHEEL
minimal_cli-0.0.1.dist-info/entry_points.txt
minimal_cli-0.0.1.dist-info/top_level.txt
minimal_cli-0.0.1.dist-info/RECORD
