Metadata-Version: 2.4
Name: minimal-cli
Version: 0.0.1
Requires-Dist: click
